{
  "collapse-filter": false,
  "search": "",
  "showTags": false,
  "showAttachments": false,
  "hideUnresolved": false,
  "showOrphans": true,
  "collapse-color-groups": true,
  "colorGroups": [
    {
      "query": "path:Golang",
      "color": {
        "a": 1,
        "rgb": 14048348
      }
    },
    {
      "query": "path:MySQL",
      "color": {
        "a": 1,
        "rgb": 14069084
      }
    },
    {
      "query": "path:PHP",
      "color": {
        "a": 1,
        "rgb": 11392604
      }
    },
    {
      "query": "path:\"VS Code\"",
      "color": {
        "a": 1,
        "rgb": 6084188
      }
    },
    {
      "query": "path:前端",
      "color": {
        "a": 1,
        "rgb": 6084269
      }
    },
    {
      "query": "path:终端",
      "color": {
        "a": 1,
        "rgb": 6073814
      }
    },
    {
      "query": "path:前端/词汇",
      "color": {
        "a": 1,
        "rgb": 6053078
      }
    },
    {
      "query": "path:终端/Linux",
      "color": {
        "a": 1,
        "rgb": 11361494
      }
    }
  ],
  "collapse-display": false,
  "showArrow": true,
  "textFadeMultiplier": 0,
  "nodeSizeMultiplier": 2.20347493489583,
  "lineSizeMultiplier": 3.98395182291667,
  "collapse-forces": true,
  "centerStrength": 0.565981657608696,
  "repelStrength": 10.6640625,
  "linkStrength": 1,
  "linkDistance": 154,
  "scale": 0.7871676886662887,
  "close": true
}